{
  "chapterId": "ch_04",
  "title": "இருண்ட காலச் சோழ மன்னர்",
  "sections": [
    {
      "type": "paragraph",
      "content": "சங்க காலச் சோழ மரபு கி.பி. மூன்றாம் நூற்றாண்டில் நலிவுற்றது. அதன்பிறகு சோழர் குடியில் தோன்றிய சிலர் குறுநில மன்னராகவும், படைத்தலைவராகவும், பெருநிலக்கிழாராகவும் சோழநாட்டின் பல பகுதிகளில் வாழ்ந்துவந்தனர். இக்காலத்தில் உறையூரைத் தலைநகராகக் கொண்டு ஆண்டவொரு சோழ மன்னனைப் பற்றிய குறிப்பு பெரியபுராணத்தில் சிறப்பிடம் பெற்றுள்ளது. புகழ்ச்சோழர் என்பது அவனுடைய பெயர். அவனுக்குக் கொங்கரும் குடகு நாட்டு அரசரும் திறை செலுத்தி வந்தனர். பகைவர் தலைகளுள் சிறிய சடையுடைய தலை ஒன்றைக் கண்டு, தன் வீரர் சிவனடியார் ஒருவரைக் கொன்று விட்டதாக எண்ணி வருந்தி, அவன் தீக்குளித்து மாய்ந்தான். அவனுடைய காலம் கி.பி. 400க்கும் 600க்கும் இடைப்பட்டதாகலாம்."
    },
    {
      "type": "heading",
      "content": "பாண்டியரும் சோழரும்"
    },
    {
      "type": "paragraph",
      "content": "நின்றசீர் நெடுமாறன் என்று போற்றப்படும் பாண்டியன் மாறவர்மன் அரிகேசரியாவான். அவனுடைய (கி.பி. 610-670) பட்டத்தரசியான மங்கையர்க்கரசியின் தந்தையாரை 'மணிமுடிச் சோழர்' என்று சேக்கிழார் குறிப்பிட்டுள்ளார். சுந்தரரும் சேரமான் பெருமாள் நாயனாரும் மதுரைக்குச் சென்றபொழுது அங்குப் பாண்டியன் மகளை மணம் புரிந்து வாழ்ந்த சோழ இளவரசன் ஒருவனைக் கண்டதாகத் தெரிகிறது."
    },
    {
      "type": "paragraph",
      "content": "வைணவ மரபினைத் தெளிவுறுத்தும் நூல் 'குருபரம்பரை' என்பதாகும். தொண்டரடிப்பொடி ஆழ்வாரைக் கவர்ந்த தேவதேவி என்ற கணிகை, சோழனுடைய உறையூர் அவைக்களத்தில் இருந்து திரும்பி வந்ததாக அந்நூலில் குறிப்பு ஒன்று காணப்படுகிறது. 'மனிதரை மணம் புரியேன்' என்னும் சூளுரையுடன் வாழ்ந்த 'உறையூர் நாச்சியார்' என்னும் நங்கை, உறையூரை ஆண்ட சூரிய குலத்துதித்த தருமவர்மன் என்ற சோழ மன்னனின் மகள் என்பது இங்குக் கருதத்தக்கது. திருமங்கையாழ்வார் ஒரு சோழ அரசனிடத்துப் படைத்தலைவராகவே தம்முடைய வாழ்க்கையைத் தொடங்கினார் என்பதும் இங்கு நினைவுகூர்தற்குரியதாகும்."
    },
    {
      "type": "paragraph",
      "content": "மேலே குறிப்பிடப் பெற்ற சோழ மன்னர்கள் கி.பி. ஐந்தாம் நூற்றாண்டிற்கும் ஒன்பதாம் நூற்றாண்டிற்கும் இடையில் வாழ்ந்தவராவர். மேற்கண்ட இலக்கியச் சான்றுகள், களப்பிரர் இடைவீட்டுக் காலம் என்று சொல்லப்படும் கி.பி. நான்காம், ஐந்தாம், ஆறாம் நூற்றாண்டுகளிலும், பல்லவப் பேரரசு காலத்திலும் சோழ அரச மரபு அழிந்து ஒழியாமல், புத்துயிர் பெறுவதற்கு ஏற்ற காலத்தை எதிர்நோக்கிக் காத்திருந்ததைத் தெரிவிக்கின்றன."
    },
    {
      "type": "paragraph",
      "content": "கி.பி. ஐந்தாம் நூற்றாண்டின் இறுதியில், காவிரிப்பூம்பட்டினத்தில் ஒரு மண்டபத்தில் அமர்ந்து, புத்ததத்த மகாதேரர் 'விநயவிநிச்சயம்' என்னும் பௌத்த சமய நூலை இயற்றினார். அப்பொழுது காவிரிப்பூம்பட்டினத்தின் ஒரு பகுதியைக் கடல் கொண்டு போய்விட்டதாகத் தம் நூலில் அவர் குறிப்பிட்டுள்ளார். அக்காலத்திய சோழ நாட்டில் இரு பெரும் பௌத்த விகாரைகள் கட்டப்பட்டிருந்தன என்று அவர் தெரிவித்துள்ளார்."
    },
    {
      "type": "heading",
      "content": "பல்லவரும் சோழரும்"
    },
    {
      "type": "paragraph",
      "content": "பல்லவர் காலத்திய செப்பேடுகள், சோழரைப் பற்றிய செய்திகள் சிலவற்றைத் தெரிவிக்கின்றன. வேலூர்ப்பாளையம் செப்பேட்டில் 'சோழப் படையாகிய கடலுக்கு, வடவைக்கனலாகப் புத்தவர்மன் விளங்கினான்' என்னுங் குறிப்பொன்று காணப்படுகிறது. அவ்வரசன் கி.பி. ஐந்தாம் நூற்றாண்டின் தொடக்கத்தில் வாழ்ந்தவனாகலாம். காவிரியால் வளமுற்றுத் திகழும் சோழநாட்டைச் சிம்மவிஷ்ணு (கி.பி. 575 - 600) கைப்பற்றியதாகச் சொல்லப்படுகிறது. மகேந்திரவர்மன் (கி.பி. 600 - 630) சோழ நாட்டைத் தன்னுடைய ஆதிக்கத்தின்கீழ்க் கொண்டு வந்தமை குறித்து மகிழ்வுற்றான்."
    },
    {
      "type": "paragraph",
      "content": "திருச்சிராப்பள்ளி மலையில் காணப்படும் அவனுடைய கல்வெட்டுக்கள், சோழநாட்டின் முடிவேந்தனாக அவனைப் போற்றுகின்றன. பரமேசுவரவர்மனின் கூரம் செப்பேடு, அவ்வரசன் கைப்பற்றிய நாடுகளுள் ஒன்றாகச் சோழநாட்டைக் குறிப்பிடுகிறது. சாளுக்கிய விக்கிரமாதித்தனுடைய கத்வெல் பட்டயம் (கி.பி. 674) காவிரியின் தென்கரையில் உள்ள சோழர் தலைநகரமாகிய உறையூரில், தமிழகத்தில் பெற்ற பெருவெற்றிக்குப் பின்னர் அவன் தங்கியிருந்ததாகத் தெரிவிக்கிறது."
    },
    {
      "type": "paragraph",
      "content": "பாண்டிய மன்னர் வழங்கிய செப்பேடுகளும், பொறித்த கல்வெட்டுகளும் சோழநாட்டையும், சோழமன்னரையும் சுட்டுகின்றன. வேள்விக்குடிச் செப்பேட்டில் பாண்டியன் கோச்சடையன் ரணதீரன் (கி.பி. 670-710) சோழநாட்டின் ஒரு பகுதியைக் கைப்பற்றியதோடு, 'செம்பியன் சோழன்' என்னும் பட்டப் பெயர்களையும் சூட்டிக்கொண்டான் என்று அறிவிக்கிறது."
    },
    {
      "type": "paragraph",
      "content": "மாறஞ்சடையனின் திருச்சிராப்பள்ளிக் கல்வெட்டு, அவனைச் சந்திர குலத்திற்கும் சூரிய குலத்திற்கும் திலகம் போல் விளங்குபவன் என்று மொழிகிறது. சின்னமனூர்ச் செப்பேட்டில் குடந்தைக்கு அருகில் சீமாற சீவல்லபனிடம் (835-862) தோல்வியுற்ற பல்லவ மன்னனின் உதவிக்கு வந்தவருள் சோழரும் இருந்ததாகத் தெரிவிக்கிறது."
    },
    {
      "type": "paragraph",
      "content": "இத்தகைய தொல்லியல் செப்பேட்டு, கல்வெட்டுச் சான்றுகளால் சோழ அரச மரபின் புகழொளி இவ்விடைக் காலத்தில் குன்றி இருந்தமையும் அது அடியோடு அழிந்தொழியாமல், நீறு பூத்த நெருப்பாக இருந்துவந்தமையும் புலனாகின்றன."
    },
    {
      "type": "paragraph",
      "content": "பூம்புகார், கடல் கொள்ளப்பட்ட பிறகு உறையூரே சோழருடைய தலைநகரமாக இருந்தது. அதை உரகபுரம் என்னும் பெயரால் பல்லவ, சாளுக்கிய அரசர்களின் செப்பேடுகள் சுட்டுகின்றன. உறையூரையும் பறிகொடுத்த பின்னர், சோழ மரபைச் சேர்ந்தவர்கள் கும்பகோணத்திற்கு அருகில் உள்ள நந்திபுரம் எனப்பட்ட பழையாறையில் வாழ்ந்து வந்தனர். விசயாலயன் தஞ்சையைக் கைப்பற்றிச் சோழ நாட்டின் தலைநகராக அதை அமைத்துக் கொண்ட பிறகும், சோழ அரச குடும்பத்தினர் அந்நகரில் வாழ்ந்து வந்தனர்."
    },
    {
      "type": "heading",
      "content": "தெலுங்கச் சோழர்கள்"
    },
    {
      "type": "paragraph",
      "content": "தமிழகத்தில் பண்டைச் சோழ அரச மரபின் ஆட்சி கி.பி. நான்காம் நூற்றாண்டு அளவில் நலிவுற்றது. அதன் பிறகு ஆந்திர மாநிலத்தில் கடப்பை, கர்நூல் மாவட்டங்களில் பாய்ந்தோடும் குண்டேறு ஆற்றின் பள்ளத்தாக்குப் பகுதியில் கி.பி. ஆறாம் நூற்றாண்டு அளவில் ஓர் அரசு தோன்றியது. அப்பகுதிக்கு 'ரேநாண்டு ஏழாயிரம்' என்பது பெயர். அதனால், அவ்வரச மரபிற்கு ரேநாண்டுச் சோழ மரபு என்னும் பெயருண்டாயிற்று. அவ்வரச மரபினரை 'பொத்தப்பிச் சோழர்' என்று சுட்டுவதும் உண்டு."
    },
    {
      "type": "paragraph",
      "content": "அவ்வரச மரபினர் சோழப் பெருவேந்தன் கரிகாலனின் கால்வழியிலே வந்தவர்கள் தாங்கள் என்று பெருமிதத்தோடு பேசுகின்றனர். கரிகாலனுக்கும் தெலுங்கு நாட்டு அரச குடும்பத்தினருக்கும் எவ்வாறு, எப்பொழுது தொடர்பு உண்டாயிற்று என்பதை நாம் உறுதியாகக் கூற இயலவில்லை. சோழப் பேரரசன் கரிகாலனுடைய ஆட்சி ஆந்திர மாநிலத்தில் கர்நூல் வரை பரவியிருந்தது என்றும், அக்காலத்தில் சோழ அரச குடும்பத்தைச் சேர்ந்தவர் சிலர் அப்பகுதியில் அரசப் பிரதிநிதிகளாக வாழ்ந்திருக்க வேண்டும் என்றும் சில அறிஞர்கள் கருதுகின்றனர். அவர்களுடைய வழித்தோன்றல்களே கி.பி. ஆறாம் நூற்றாண்டு அளவில் எழுச்சியுற்று ஓர் அரசை நிறுவி இருக்க வேண்டும் என்பது அவர்களுடைய நம்பிக்கையாகும்."
    },
    {
      "type": "paragraph",
      "content": "இக்கருத்து பொருத்தமற்ற ஒன்று என்பது மற்றோர் ஆசிரியருடைய கருத்தாகும். ரேநாண்டுச் சோழனான புண்ணியகுமாரன் வழங்கிய 'மாலேபாடு' செப்பேட்டின் வாசகத்திலிருந்து, அக்காலத்தில் (கி.பி. ஏழாம் நூற்றாண்டு) தமிழகச் சோழ அரச மரபோடு நேரடியான தொடர்பும் உறவும் அவர்களுக்கு இருந்து வந்தமை புலனாகின்றது. எனவே, சிம்மவிஷ்ணுவின் மரபினர் காஞ்சியில் ஆட்சி புரிந்த காலத்தில் பல்லவ இராச்சியத்தின் வழியாகச் சோழர் வடக்கு நோக்கிச் சென்றிருக்கலாம் என்பது அவ்வாசிரியர் தரும் விளக்கமாகும். இத்தொடர்பு கரிகாலன் காலம் முதற்கொண்டே இருந்து வந்தது என்று கருத அம்மன்னர்களின் கல்வெட்டுகளே இடம் தருகின்றன."
    },
    {
      "type": "paragraph",
      "content": "சங்க காலத்திற்குப் பின்னர் சிறப்புற்ற பாண்டிய மரபில் வந்த சில மன்னர்கள் தெலுங்கச் சோழரின் பெண்களை மணம் செய்து கொண்டனர். அவர்களுள் சிறப்பாகச் சீமாற சீவல்லபன் இங்குக் குறிப்பிடத்தக்கவனாவான். அவன் பொத்தப்பிக் குலத்துச் சோழனான சீகண்டன் மகள் அக்களநிம்மடியை மணம் செய்து கொண்டான். அவளுக்குப் பிறந்தவனே தளவாய்புரச் செப்பேட்டை வழங்கிய பராந்தக வீரநாராயணன் ஆவான். அச்சீகண்டன் தெலுங்கச் சோழர் கிளையிலே சிறப்புற்று விளங்கினான். அவன் வழங்கிய செப்பேடு ஒன்று சென்னை அரசினர் அரும்பொருள் காட்சியகத்தில் இருக்கிறது. அவன் கி.பி. ஒன்பதாம் நூற்றாண்டின் முற்பகுதியில் வாழ்ந்ததாகத் தெரிகிறது."
    },
    {
      "type": "paragraph",
      "content": "இராசராச சோழனுடைய தந்தையான இரண்டாம் பராந்தகன் வழங்கிய செப்பேட்டிற்கு, 'அன்பில் செப்பேடு' என்பது பெயர். அதில், தஞ்சை அரச மரபினை நிறுவிய விசயாலயனுக்கு முன்னர் வாழ்ந்த மூதாதையருடைய பெயர்கள் காலவரன்முறைப்படி குறிப்பிடப்பட்டுள்ளன. அவ்வரிசையில் சீகண்டனுடைய பெயர் விசயாலயனுக்கு முன்னதாக இடம் பெற்றிருக்கிறது. இதனால் ரேநாண்டுச் சோழர்களுக்கும் தமிழகத்தின் சோழ மரபிற்கும் நெருக்கமான தொடர்பு இருந்து வந்தமை புலனாகின்றது. மற்றும், தஞ்சைச் சோழர்கள், பொத்தப்பிச் சோழரைத் தங்கள் குடியின் முன்னோர் என்று கூறிக்கொள்வதில் பெருமிதம் கொண்டனர் என்பதும் அறியப்படுகிறது."
    },
    {
      "type": "paragraph",
      "content": "இந்தச் சோழ மரபு தமிழகத்தில் சோழர் வலிகுன்றி இருந்த காலத்தில் அம்மரபின் தொன்மைச் சிறப்பினையும் சீர்த்தியையும் உலகிற்கு உணர்த்தும் அரிய தொண்டினை ஆற்றியுள்ளமை நம்மை வியப்பில் ஆழ்த்துகிறது. 'இக்காலத்தில் தமிழ்நாட்டில் சோழர் குடியினர் வாழவில்லை; கடப்பை கர்நூல் மாவட்டங்களிலேயே வாழ்ந்தனர்' [19] என்னும் கருத்து பொருத்தமற்றது என்பதற்கு இவ்வியலின் முதற்பகுதியில் தரப்பட்டுள்ள சான்றுகளே போதுமானவையாகும்."
    }
  ]
}